Metadata-Version: 2.4
Name: dbt-starrocks
Version: 1.10.1
Summary: The Starrocks adapter plugin for dbt
Home-page: https://github.com/StarRocks/dbt-starrocks/
Author: fujianhj, long2ice, astralidea
Author-email: fujianhj@gmail.com, long2ice@gmail.com, astralidea@163.com
Classifier: Development Status :: 5 - Production/Stable
Classifier: License :: OSI Approved :: Apache Software License
Classifier: Operating System :: Microsoft :: Windows
Classifier: Operating System :: MacOS :: MacOS X
Classifier: Operating System :: POSIX :: Linux
Classifier: Programming Language :: Python :: 3.9
Classifier: Programming Language :: Python :: 3.10
Classifier: Programming Language :: Python :: 3.11
Classifier: Programming Language :: Python :: 3.12
Requires-Python: >=3.9,<3.13
Requires-Dist: dbt-core>=1.9.0
Requires-Dist: mysql-connector-python>=8.1
Dynamic: author
Dynamic: author-email
Dynamic: classifier
Dynamic: description
Dynamic: description-content-type
Dynamic: home-page
Dynamic: requires-dist
Dynamic: requires-python
Dynamic: summary
